dependenpy-3.3.3.dist-info/METADATA
dependenpy-3.3.3.dist-info/WHEEL
dependenpy-3.3.3.dist-info/entry_points.txt
dependenpy-3.3.3.dist-info/licenses/LICENSE
dependenpy/__init__.py
dependenpy/__main__.py
dependenpy/_internal/__init__.py
dependenpy/_internal/cli.py
dependenpy/_internal/debug.py
dependenpy/_internal/dsm.py
dependenpy/_internal/finder.py
dependenpy/_internal/helpers.py
dependenpy/_internal/node.py
dependenpy/_internal/plugins.py
dependenpy/_internal/structures.py
dependenpy/cli.py
dependenpy/debug.py
dependenpy/dsm.py
dependenpy/finder.py
dependenpy/helpers.py
dependenpy/node.py
dependenpy/plugins.py
dependenpy/py.typed
dependenpy/structures.py
dependenpy-3.3.3.dist-info/RECORD
