Metadata-Version: 2.4
Name: dependenpy
Version: 3.3.3
Summary: Show the inter-dependencies between modules of Python packages.
Keywords: dependency,analysis,matrix,dsm
Author-Email: =?utf-8?q?Timoth=C3=A9e_Mazzucotelli?= <dev@pawamoy.fr>
License-Expression: ISC
License-File: LICENSE
Classifier: Development Status :: 4 - Beta
Classifier: Intended Audience :: Developers
Classifier: Programming Language :: Python
Classifier: Programming Language :: Python :: 3
Classifier: Programming Language :: Python :: 3 :: Only
Classifier: Programming Language :: Python :: 3.9
Classifier: Programming Language :: Python :: 3.10
Classifier: Programming Language :: Python :: 3.11
Classifier: Programming Language :: Python :: 3.12
Classifier: Programming Language :: Python :: 3.13
Classifier: Programming Language :: Python :: 3.14
Classifier: Topic :: Documentation
Classifier: Topic :: Software Development
Classifier: Topic :: Utilities
Classifier: Typing :: Typed
Project-URL: Homepage, https://pawamoy.github.io/dependenpy
Project-URL: Documentation, https://pawamoy.github.io/dependenpy
Project-URL: Changelog, https://pawamoy.github.io/dependenpy/changelog
Project-URL: Repository, https://github.com/pawamoy/dependenpy
Project-URL: Issues, https://github.com/pawamoy/dependenpy/issues
Project-URL: Discussions, https://github.com/pawamoy/dependenpy/discussions
Project-URL: Gitter, https://gitter.im/dependenpy/community
Project-URL: Funding, https://github.com/sponsors/pawamoy
Requires-Python: >=3.9
Requires-Dist: colorama>=0.4.5
